write_struct/__init__.py
write_struct/main.py
write_struct/prompts.py
write_struct-2025.12.21200316.dist-info/METADATA
write_struct-2025.12.21200316.dist-info/WHEEL
write_struct-2025.12.21200316.dist-info/top_level.txt
write_struct-2025.12.21200316.dist-info/RECORD
