Metadata-Version: 2.4
Name: write-struct
Version: 2025.12.21200316
Summary: write-struct transforms user-submitted text into structured, formatted content for improved readability and consistency.
Author-email: write-struct <hi@eugene.plus>
License: MIT
Project-URL: Homepage, https://github.com/chigwell/write-struct
Requires-Python: >=3.9
Requires-Dist: langchain-llm7>=0.0.0
Requires-Dist: llmatch-messages>=0.0.0
Requires-Dist: langchain-core>=0.3.0
